eruza/__init__.py
eruza/app.py
eruza-0.8.data/scripts/eruza
eruza-0.8.dist-info/LICENSE
eruza-0.8.dist-info/METADATA
eruza-0.8.dist-info/WHEEL
eruza-0.8.dist-info/top_level.txt
eruza-0.8.dist-info/RECORD
